s3helper/__init__.py
s3helper/s3_helper.py
bettertool-0.1.0.dist-info/METADATA
bettertool-0.1.0.dist-info/WHEEL
bettertool-0.1.0.dist-info/top_level.txt
bettertool-0.1.0.dist-info/RECORD
